genid/__about__.py
genid/__init__.py
genid/generators.py
genid/nanoid.py
genid/nuid.py
genid/objectid.py
genid/ulid/__init__.py
genid/ulid/base32.py
genid/ulid/constants.py
genid-1.0.1.dist-info/METADATA
genid-1.0.1.dist-info/WHEEL
genid-1.0.1.dist-info/top_level.txt
genid-1.0.1.dist-info/RECORD
