Metadata-Version: 2.1
Name: genid
Version: 1.0.1
Author-email: Guillaume Charbonnier <guillaume.charbonnier@araymond.com>
License: MIT
Project-URL: Repository, https://github.com/charbonnierg/genid
Project-URL: Issues, https://github.com/charbonnierg/genid/issues
Classifier: Programming Language :: Python :: 3
Classifier: License :: OSI Approved :: Apache Software License
Requires-Python: <4.0,>=3.8
Provides-Extra: build
Requires-Dist: build ; extra == 'build'
Requires-Dist: invoke ; extra == 'build'
Requires-Dist: pip-tools ; extra == 'build'
Provides-Extra: dev
Requires-Dist: black ; extra == 'dev'
Requires-Dist: isort ; extra == 'dev'
Requires-Dist: invoke ; extra == 'dev'
Requires-Dist: flake8 ; extra == 'dev'
Requires-Dist: mypy ; extra == 'dev'
Requires-Dist: pytest ; extra == 'dev'
Requires-Dist: pytest-asyncio ; extra == 'dev'
Requires-Dist: pytest-cov ; extra == 'dev'
Requires-Dist: types-setuptools ; extra == 'dev'
Provides-Extra: docs
Requires-Dist: mkdocs-gen-files ; extra == 'docs'
Requires-Dist: mkdocs-literate-nav ; extra == 'docs'
Requires-Dist: mkdocs-material ; extra == 'docs'
Requires-Dist: mkdocs-section-index ; extra == 'docs'
Requires-Dist: mkdocstrings[python] ; extra == 'docs'
Requires-Dist: pymdown-extensions ; extra == 'docs'
